async_gui/__init__.py
async_gui/compat.py
async_gui/engine.py
async_gui/gevent_tasks.py
async_gui/tasks.py
async_gui/toolkits/__init__.py
async_gui/toolkits/_qt.py
async_gui/toolkits/kivy.py
async_gui/toolkits/pygtk.py
async_gui/toolkits/pyqt.py
async_gui/toolkits/pyside.py
async_gui/toolkits/tk.py
async_gui/toolkits/wx.py
uncrumpled_async_gui-0.1.1.dist-info/DESCRIPTION.rst
uncrumpled_async_gui-0.1.1.dist-info/METADATA
uncrumpled_async_gui-0.1.1.dist-info/RECORD
uncrumpled_async_gui-0.1.1.dist-info/WHEEL
uncrumpled_async_gui-0.1.1.dist-info/metadata.json
uncrumpled_async_gui-0.1.1.dist-info/top_level.txt
