Metadata-Version: 2.0
Name: uncrumpled-async-gui
Version: 0.1.1
Summary: Easy threading and multiprocessing for GUI applications
Home-page: https://github.com/reclosedev/async_gui
Author: Roman Haritonov
Author-email: reclosedev@gmail.com
License: BSD License
Keywords: GUI,thread,coroutine,futures,async
Platform: UNKNOWN
Classifier: License :: OSI Approved :: BSD License
Classifier: Development Status :: 4 - Beta
Classifier: Intended Audience :: Developers
Classifier: Topic :: Software Development :: Libraries :: Python Modules
Classifier: Programming Language :: Python
Classifier: Programming Language :: Python :: 2.7
Classifier: Programming Language :: Python :: 3
